jinja2_component_macros/__init__.py
jinja2_component_macros/helpers.py
jinja2_component_macros/jinja.py
jinja2_component_macros/py.typed
jinja2_component_macros-2025.1.dist-info/licenses/LICENSE
jinja2_component_macros-2025.1.dist-info/WHEEL
jinja2_component_macros-2025.1.dist-info/METADATA
jinja2_component_macros-2025.1.dist-info/RECORD
