Metadata-Version: 2.4
Name: jinja2-component-macros
Version: 2025.1
Summary: A Jinja2 extension for writing component-like HTML that gets converted into Jinja macro calls
Keywords: jinja2,templates,components,html,macros,web
Author: Dan Sloan
Author-email: Dan Sloan <dan@dansloan.dev>
License-Expression: MIT
License-File: LICENSE
Classifier: Development Status :: 4 - Beta
Classifier: Environment :: Web Environment
Classifier: Intended Audience :: Developers
Classifier: License :: OSI Approved :: MIT License
Classifier: Programming Language :: Python :: 3
Classifier: Programming Language :: Python :: 3.10
Classifier: Programming Language :: Python :: 3.11
Classifier: Programming Language :: Python :: 3.12
Classifier: Programming Language :: Python :: 3.13
Classifier: Topic :: Internet :: WWW/HTTP :: Dynamic Content
Classifier: Topic :: Software Development :: Libraries :: Python Modules
Classifier: Topic :: Text Processing :: Markup :: HTML
Classifier: Typing :: Typed
Requires-Dist: jinja2>=3.1.0
Requires-Python: >=3.10
Project-URL: Changelog, https://github.com/luciddan/jinja2-component-macros/blob/main/CHANGELOG.md
Project-URL: Homepage, https://github.com/luciddan/jinja2-component-macros
Project-URL: Issues, https://github.com/luciddan/jinja2-component-macros/issues
Project-URL: Repository, https://github.com/luciddan/jinja2-component-macros
